<?xml version="1.0"?>
<!-- This file is part of Tryton.  The COPYRIGHT file at the top level of
this repository contains the full copyright notices and license terms. -->
<tryton>
    <data>

        <record model="ir.ui.view" id="product_product_shipment_form">
            <field name="model">product.product</field>
            <field name="type">form</field>
            <field name="inherit" ref="product.product_view_form"/>
            <field name="arch" type="xml">
                <![CDATA[
                <data>
                    <xpath expr="/form/notebook" position="inside">
                        <page string="Custom Details" id="custom_details">
                            <label name="customs_desc"/>
                            <field name="customs_desc"/>
                            <label name="customs_value"/>
                            <field name="customs_value"/>
                        </page>
                    </xpath>
                </data>
                ]]>
            </field>
        </record>
        
    </data>
</tryton>

